LICENSE
README.rst
francedata/__init__.py
francedata/admin.py
francedata/api.py
francedata/apps.py
francedata/management/__init__.py
francedata/management/commands/__init__.py
francedata/management/commands/banatic_import.py
francedata/management/commands/cog_import.py
francedata/management/commands/files_import.py
francedata/migrations/0001_initial.py
francedata/migrations/0002_auto_20211101_1541.py
francedata/migrations/0003_datamapping_datasourcefile_historicaldatamapping_squashed_0007_alter_datamapping_options.py
francedata/migrations/0004_alter_datayear_options.py
francedata/migrations/0005_auto_20230111_1734.py
francedata/migrations/__init__.py
francedata/models/__init__.py
francedata/models/collectivity.py
francedata/models/meta.py
francedata/models/sources.py
francedata/resources/__init__.py
francedata/resources/departements-siren.csv
francedata/resources/regions-siren.csv
francedata/schemas.py
francedata/services/__init__.py
francedata/services/banatic.py
francedata/services/cog.py
francedata/services/datagouv.py
francedata/services/django_admin.py
francedata/services/utils.py
francedata/services/validators.py
francedata/templates/desl_imports/admin/query_changeform.html
francedata/tests/__init__.py
francedata/tests/services/tests_banatic.py
francedata/tests/services/tests_cog.py
francedata/tests/services/tests_utils.py
francedata/tests/services/tests_validators.py
francedata/tests/testdata/sample_communes.csv
francedata/tests/testdata/sample_communes.xlsx
francedata/tests/testdata/sample_data.py
francedata/tests/testdata/sample_epci.xlsx
francedata/tests/tests_models.py
francedata/views.py
django_francedata-0.16.2.dist-info/METADATA
django_francedata-0.16.2.dist-info/LICENSE
django_francedata-0.16.2.dist-info/WHEEL
django_francedata-0.16.2.dist-info/RECORD
