Metadata-Version: 2.1
Name: django-francedata
Version: 0.16.2
Summary: A Django app to provide a database structure, API and import scripts to manage French communes, intercommunalités, départements and régions, with their structure and data from Insee and the DGCL.
Home-page: https://github.com/entrepreneur-interet-general/django-francedata
License: AGPL-3
Keywords: django
Author: Sylvain Boissel
Author-email: sylvain.boissel@beta.gouv.fr
Requires-Python: >=3.8,<4.0
Classifier: Development Status :: 3 - Alpha
Classifier: Environment :: Web Environment
Classifier: Framework :: Django
Classifier: Framework :: Django :: 3.2
Classifier: Intended Audience :: Developers
Classifier: License :: OSI Approved :: GNU Affero General Public License v3 or later (AGPLv3+)
Classifier: License :: Other/Proprietary License
Classifier: Operating System :: OS Independent
Classifier: Programming Language :: Python :: 3
Classifier: Programming Language :: Python :: 3.8
Classifier: Programming Language :: Python :: 3.9
Classifier: Programming Language :: Python :: 3.10
Classifier: Programming Language :: Python :: 3.11
Classifier: Programming Language :: Python :: 3
Classifier: Programming Language :: Python :: 3.8
Classifier: Programming Language :: Python :: 3.9
Classifier: Topic :: Internet :: WWW/HTTP
Classifier: Topic :: Internet :: WWW/HTTP :: Dynamic Content
Requires-Dist: Django (>=3.2.7,<4.0.0)
Requires-Dist: Unidecode (>=1.2.0,<2.0.0)
Requires-Dist: django-json-widget (>=1.1.1,<2.0.0)
Requires-Dist: django-ninja (>=0.14.0,<0.15.0)
Requires-Dist: django-simple-history (>=3.0.0,<4.0.0)
Requires-Dist: openpyxl-dictreader (>=0.1.3,<0.2.0)
Requires-Dist: pandas (>=1.3.4,<2.0.0)
Requires-Dist: psycopg2 (>=2.9.2,<3.0.0)
Requires-Dist: python-stdnum (>=1.16,<2.0)
Requires-Dist: requests (>=2.26.0,<3.0.0)
Requires-Dist: xlrd (>=2.0.1,<3.0.0)
Project-URL: Repository, https://github.com/entrepreneur-interet-general/django-francedata
